[{"id":9222968140497180875,"category":{"id":0,"name":"string"},"name":"fish","photoUrls":["string"],"tags":[{"id":0,"name":"string"}],"status":"available"},{"id":9222968140497180876,"category":{"id":0,"name":"string"},"name":"fish","photoUrls":["string"],"tags":[{"id":0,"name":"string"}],"status":"available"},{"id":9222968140497180883,"category":{"id":0,"name":"string"},"name":"doggie","photoUrls":["string"],"tags":[{"id":0,"name":"string"}],"status":"available"},{"id":9222968140497180884,"category":{"id":0,"name":"string"},"name":"doggie","photoUrls":["string"],"tags":[{"id":0,"name":"string"}],"status":"available"},{"id":9222968140497180885,"category":{"id":0,"name":"string"},"name":"doggie","photoUrls":["string"],"tags":[{"id":0,"name":"string"}],"status":"available"},{"id":9222968140497180886,"category":{"id":0,"name":"string"},"name":"doggie","photoUrls":["string"],"tags":[{"id":0,"name":"string"}],"status":"available"},{"id":9222968140497180887,"category":{"id":0,"name":"string"},"name":"doggie","photoUrls":["string"],"tags":[{"id":0,"name":"string"}],"status":"available"},{"id":9222968140497180888,"category":{"id":0,"name":"string"},"name":"doggie","photoUrls":["string"],"tags":[{"id":0,"name":"string"}],"status":"available"},{"id":9222968140497180889,"category":{"id":0,"name":"string"},"name":"doggie","photoUrls":["string"],"tags":[{"id":0,"name":"string"}],"status":"available"},{"id":9222968140497180890,"category":{"id":0,"name":"string"},"name":"doggie","photoUrls":["string"],"tags":[{"id":0,"name":"string"}],"status":"available"},{"id":9222968140497180891,"category":{"id":0,"name":"string"},"name":"doggie","photoUrls":["string"],"tags":[{"id":0,"name":"string"}],"status":"available"},{"id":9222968140497180892,"category":{"id":0,"name":"string"},"name":"doggie","photoUrls":["string"],"tags":[{"id":0,"name":"string"}],"status":"available"},{"id":9222968140497180893,"category":{"id":0,"name":"string"},"name":"doggie","photoUrls":["string"],"tags":[{"id":0,"name":"string"}],"status":"available"},{"id":9222968140497180894,"category":{"id":0,"name":"string"},"name":"doggie","photoUrls":["string"],"tags":[{"id":0,"name":"string"}],"status":"available"},{"id":223,"category":{"id":7,"name":"cats"},"name":"cat2","photoUrls":["https://www.google.com/imgres?imgurl=https%3A%2F%2Fmedia.npr.org%2Fassets%2Fimg%2F2021%2F08%2F11%2Fgettyimages-1279899488_wide-f3860ceb0ef19643c335cb34df3fa1de166e2761-s1100-c50.jpg&imgrefurl=https%3A%2F%2Fwww.npr.org%2F2021%2F08%2F10%2F1026508261%2Fdoes-your-cat-like-you-or-just-tolerate-you&tbnid=SmV-DRygMSkY4M&vet=12ahUKEwj--qubiqz5AhXEVDUKHb1uDsIQMygNegUIARDYAQ..i&docid=Wk-fR7Ddh__zKM&w=1100&h=618&q=cats&ved=2ahUKEwj--qubiqz5AhXEVDUKHb1uDsIQMygNegUIARDYAQ"],"tags":[{"id":112,"name":"string"}],"status":"available"},{"id":9222968140497180895,"category":{"id":0,"name":"string"},"name":"fish","photoUrls":["string"],"tags":[{"id":0,"name":"string"}],"status":"available"},{"id":9222968140497180896,"category":{"id":0,"name":"string"},"name":"doggie","photoUrls":["string"],"tags":[{"id":0,"name":"string"}],"status":"available"},{"id":9222968140497180897,"category":{"id":0,"name":"string"},"name":"doggie","photoUrls":["string"],"tags":[{"id":0,"name":"string"}],"status":"available"},{"id":9222968140497180898,"category":{"id":0,"name":"string"},"name":"doggie","photoUrls":["string"],"tags":[{"id":0,"name":"string"}],"status":"available"},{"id":9222968140497180899,"category":{"id":0,"name":"string"},"name":"fish","photoUrls":["string"],"tags":[{"id":0,"name":"string"}],"status":"available"},{"id":9222968140497180902,"category":{"id":0,"name":"string"},"name":"doggie","photoUrls":["string"],"tags":[{"id":0,"name":"string"}],"status":"available"},{"id":9222968140497180918,"category":{"id":0,"name":"string"},"name":"fish","photoUrls":["string"],"tags":[{"id":0,"name":"string"}],"status":"available"},{"id":9222968140497180919,"category":{"id":0,"name":"string"},"name":"fish","photoUrls":["string"],"tags":[{"id":0,"name":"string"}],"status":"available"},{"id":9222968140497180922,"category":{"id":0,"name":"sunderesan"},"name":"pig","photoUrls":["string"],"tags":[{"id":0,"name":"string"}],"status":"available"},{"id":9222968140497180923,"category":{"id":0,"name":"string"},"name":"doggie","photoUrls":["string"],"tags":[{"id":0,"name":"string"}],"status":"available"},{"id":9222968140497180924,"category":{"id":0,"name":"string"},"name":"doggie","photoUrls":["string"],"tags":[{"id":0,"name":"string"}],"status":"available"},{"id":9222968140497180925,"category":{"id":0,"name":"string"},"name":"doggie","photoUrls":["string"],"tags":[{"id":0,"name":"string"}],"status":"available"},{"id":9222968140497180926,"category":{"id":0,"name":"string"},"name":"doggie","photoUrls":["string"],"tags":[{"id":0,"name":"string"}],"status":"available"},{"id":9222968140497180927,"category":{"id":0,"name":"string"},"name":"doggie","photoUrls":["string"],"tags":[{"id":0,"name":"string"}],"status":"available"},{"id":9222968140497180928,"category":{"id":0,"name":"string"},"name":"doggie","photoUrls":["string"],"tags":[{"id":0,"name":"string"}],"status":"available"},{"id":9222968140497180929,"category":{"id":0,"name":"string"},"name":"doggie","photoUrls":["string"],"tags":[{"id":0,"name":"string"}],"status":"available"},{"id":9222968140497180930,"category":{"id":0,"name":"string"},"name":"doggie","photoUrls":["string"],"tags":[{"id":0,"name":"string"}],"status":"available"},{"id":9222968140497180931,"category":{"id":0,"name":"string"},"name":"doggie","photoUrls":["string"],"tags":[{"id":0,"name":"string"}],"status":"available"},{"id":9222968140497180932,"category":{"id":0,"name":"string"},"name":"fish","photoUrls":["string"],"tags":[{"id":0,"name":"string"}],"status":"available"},{"id":9222968140497180933,"category":{"id":0,"name":"string"},"name":"doggie","photoUrls":["string"],"tags":[{"id":0,"name":"string"}],"status":"available"},{"id":9222968140497180934,"category":{"id":0,"name":"string"},"name":"doggie","photoUrls":["string"],"tags":[{"id":0,"name":"string"}],"status":"available"},{"id":9222968140497180935,"category":{"id":0,"name":"string"},"name":"doggie","photoUrls":["string"],"tags":[{"id":0,"name":"string"}],"status":"available"},{"id":9222968140497180936,"category":{"id":0,"name":"string"},"name":"fish","photoUrls":["string"],"tags":[{"id":0,"name":"string"}],"status":"available"},{"id":9222968140497180937,"category":{"id":0,"name":"string"},"name":"doggie","photoUrls":["string"],"tags":[{"id":0,"name":"string"}],"status":"available"},{"id":9222968140497180938,"category":{"id":0,"name":"string"},"name":"doggie","photoUrls":["string"],"tags":[{"id":0,"name":"string"}],"status":"available"},{"id":9222968140497180939,"category":{"id":0,"name":"string"},"name":"doggie","photoUrls":["string"],"tags":[{"id":0,"name":"string"}],"status":"available"},{"id":9222968140497180955,"category":{"id":0,"name":"string"},"name":"doggie","photoUrls":["string"],"tags":[{"id":0,"name":"string"}],"status":"available"},{"id":9222968140497180969,"category":{"id":0,"name":"string"},"name":"fish","photoUrls":["string"],"tags":[{"id":0,"name":"string"}],"status":"available"},{"id":9222968140497180970,"category":{"id":0,"name":"string"},"name":"fish","photoUrls":["string"],"tags":[{"id":0,"name":"string"}],"status":"available"},{"id":9222968140497180974,"category":{"id":0,"name":"string"},"name":"doggie","photoUrls":["string"],"tags":[{"id":0,"name":"string"}],"status":"available"},{"id":9222968140497180975,"category":{"id":0,"name":"string"},"name":"doggie","photoUrls":["string"],"tags":[{"id":0,"name":"string"}],"status":"available"},{"id":9222968140497180976,"category":{"id":0,"name":"string"},"name":"doggie","photoUrls":["string"],"tags":[{"id":0,"name":"string"}],"status":"available"},{"id":9222968140497180977,"category":{"id":0,"name":"string"},"name":"doggie","photoUrls":["string"],"tags":[{"id":0,"name":"string"}],"status":"available"},{"id":9222968140497180978,"category":{"id":0,"name":"string"},"name":"doggie","photoUrls":["string"],"tags":[{"id":0,"name":"string"}],"status":"available"},{"id":9222968140497180979,"category":{"id":0,"name":"string"},"name":"doggie","photoUrls":["string"],"tags":[{"id":0,"name":"string"}],"status":"available"},{"id":9222968140497180980,"category":{"id":0,"name":"string"},"name":"doggie","photoUrls":["string"],"tags":[{"id":0,"name":"string"}],"status":"available"},{"id":9222968140497180981,"category":{"id":0,"name":"string"},"name":"doggie","photoUrls":["string"],"tags":[{"id":0,"name":"string"}],"status":"available"},{"id":9222968140497180982,"category":{"id":0,"name":"string"},"name":"doggie","photoUrls":["string"],"tags":[{"id":0,"name":"string"}],"status":"available"},{"id":9222968140497180983,"category":{"id":0,"name":"string"},"name":"doggie","photoUrls":["string"],"tags":[{"id":0,"name":"string"}],"status":"available"},{"id":9222968140497180984,"category":{"id":0,"name":"string"},"name":"doggie","photoUrls":["string"],"tags":[{"id":0,"name":"string"}],"status":"available"},{"id":9222968140497180985,"category":{"id":0,"name":"string"},"name":"doggie","photoUrls":["string"],"tags":[{"id":0,"name":"string"}],"status":"available"},{"id":9222968140497180986,"category":{"id":0,"name":"string"},"name":"fish","photoUrls":["string"],"tags":[{"id":0,"name":"string"}],"status":"available"},{"id":9222968140497180987,"category":{"id":0,"name":"string"},"name":"doggie","photoUrls":["string"],"tags":[{"id":0,"name":"string"}],"status":"available"},{"id":9222968140497180988,"category":{"id":0,"name":"string"},"name":"doggie","photoUrls":["string"],"tags":[{"id":0,"name":"string"}],"status":"available"},{"id":9222968140497180989,"category":{"id":0,"name":"string"},"name":"doggie","photoUrls":["string"],"tags":[{"id":0,"name":"string"}],"status":"available"},{"id":9222968140497180992,"category":{"id":0,"name":"string"},"name":"fish","photoUrls":["string"],"tags":[{"id":0,"name":"string"}],"status":"available"},{"id":9222968140497180998,"name":"doggie","photoUrls":[],"tags":[],"status":"available"},{"id":9222968140497180999,"name":"doggie","photoUrls":[],"tags":[],"status":"available"},{"id":9222968140497181000,"category":{"id":0,"name":"string"},"name":"doggie","photoUrls":["string"],"tags":[{"id":0,"name":"string"}],"status":"available"},{"id":9222968140497181013,"category":{"id":0,"name":"string"},"name":"fish","photoUrls":["string"],"tags":[{"id":0,"name":"string"}],"status":"available"},{"id":9222968140497181015,"category":{"id":0,"name":"string"},"name":"fish","photoUrls":["string"],"tags":[{"id":0,"name":"string"}],"status":"available"},{"id":9222968140497181016,"category":{"id":0,"name":"string"},"name":"doggie","photoUrls":["string"],"tags":[{"id":0,"name":"string"}],"status":"available"},{"id":9222968140497181017,"category":{"id":0,"name":"string"},"name":"doggie","photoUrls":["string"],"tags":[{"id":0,"name":"string"}],"status":"available"},{"id":9222968140497181018,"category":{"id":0,"name":"string"},"name":"doggie","photoUrls":["string"],"tags":[{"id":0,"name":"string"}],"status":"available"},{"id":9222968140497181019,"category":{"id":0,"name":"string"},"name":"doggie","photoUrls":["string"],"tags":[{"id":0,"name":"string"}],"status":"available"},{"id":9222968140497181020,"category":{"id":0,"name":"string"},"name":"doggie","photoUrls":["string"],"tags":[{"id":0,"name":"string"}],"status":"available"},{"id":9222968140497181021,"category":{"id":0,"name":"string"},"name":"doggie","photoUrls":["string"],"tags":[{"id":0,"name":"string"}],"status":"available"},{"id":9222968140497181022,"category":{"id":0,"name":"string"},"name":"doggie","photoUrls":["string"],"tags":[{"id":0,"name":"string"}],"status":"available"},{"id":9222968140497181023,"category":{"id":0,"name":"string"},"name":"doggie","photoUrls":["string"],"tags":[{"id":0,"name":"string"}],"status":"available"},{"id":9222968140497181024,"category":{"id":0,"name":"string"},"name":"doggie","photoUrls":["string"],"tags":[{"id":0,"name":"string"}],"status":"available"},{"id":9222968140497181025,"category":{"id":0,"name":"string"},"name":"doggie","photoUrls":["string"],"tags":[{"id":0,"name":"string"}],"status":"available"},{"id":9222968140497181026,"category":{"id":0,"name":"string"},"name":"doggie","photoUrls":["string"],"tags":[{"id":0,"name":"string"}],"status":"available"},{"id":9222968140497181027,"category":{"id":0,"name":"string"},"name":"doggie","photoUrls":["string"],"tags":[{"id":0,"name":"string"}],"status":"available"},{"id":9222968140497181028,"category":{"id":0,"name":"string"},"name":"doggie","photoUrls":["string"],"tags":[{"id":0,"name":"string"}],"status":"available"},{"id":9222968140497181029,"category":{"id":0,"name":"string"},"name":"doggie","photoUrls":["string"],"tags":[{"id":0,"name":"string"}],"status":"available"},{"id":9222968140497181030,"category":{"id":0,"name":"string"},"name":"doggie","photoUrls":["string"],"tags":[{"id":0,"name":"string"}],"status":"available"},{"id":9222968140497181031,"category":{"id":0,"name":"string"},"name":"fish","photoUrls":["string"],"tags":[{"id":0,"name":"string"}],"status":"available"},{"id":9222968140497181032,"category":{"id":0,"name":"string"},"name":"fish","photoUrls":["string"],"tags":[{"id":0,"name":"string"}],"status":"available"},{"id":9222968140497181056,"category":{"id":0,"name":"string"},"name":"doggie","photoUrls":["string"],"tags":[{"id":0,"name":"string"}],"status":"available"},{"id":9222968140497181059,"category":{"id":0,"name":"string"},"name":"fish","photoUrls":["string"],"tags":[{"id":0,"name":"string"}],"status":"available"},{"id":9222968140497181060,"category":{"id":0,"name":"string"},"name":"fish","photoUrls":["string"],"tags":[{"id":0,"name":"string"}],"status":"available"},{"id":9222968140497181064,"category":{"id":0,"name":"string"},"name":"doggie","photoUrls":["string"],"tags":[{"id":0,"name":"string"}],"status":"available"},{"id":9222968140497181067,"category":{"id":0,"name":"string"},"name":"doggie","photoUrls":["string"],"tags":[{"id":0,"name":"string"}],"status":"available"},{"id":9222968140497181068,"category":{"id":0,"name":"string"},"name":"doggie","photoUrls":["string"],"tags":[{"id":0,"name":"string"}],"status":"available"},{"id":9222968140497181069,"category":{"id":0,"name":"string"},"name":"doggie","photoUrls":["string"],"tags":[{"id":0,"name":"string"}],"status":"available"},{"id":9222968140497181070,"category":{"id":0,"name":"string"},"name":"doggie","photoUrls":["string"],"tags":[{"id":0,"name":"string"}],"status":"available"},{"id":9222968140497181071,"category":{"id":0,"name":"string"},"name":"doggie","photoUrls":["string"],"tags":[{"id":0,"name":"string"}],"status":"available"},{"id":9222968140497181072,"category":{"id":0,"name":"string"},"name":"doggie","photoUrls":["string"],"tags":[{"id":0,"name":"string"}],"status":"available"},{"id":9222968140497181073,"category":{"id":0,"name":"string"},"name":"doggie","photoUrls":["string"],"tags":[{"id":0,"name":"string"}],"status":"available"},{"id":9222968140497181074,"category":{"id":0,"name":"string"},"name":"doggie","photoUrls":["string"],"tags":[{"id":0,"name":"string"}],"status":"available"},{"id":9222968140497181075,"category":{"id":0,"name":"string"},"name":"doggie","photoUrls":["string"],"tags":[{"id":0,"name":"string"}],"status":"available"},{"id":9222968140497181076,"category":{"id":0,"name":"string"},"name":"doggie","photoUrls":["string"],"tags":[{"id":0,"name":"string"}],"status":"available"},{"id":9222968140497181077,"category":{"id":0,"name":"string"},"name":"doggie","photoUrls":["string"],"tags":[{"id":0,"name":"string"}],"status":"available"},{"id":9222968140497181078,"category":{"id":0,"name":"string"},"name":"doggie","photoUrls":["string"],"tags":[{"id":0,"name":"string"}],"status":"available"},{"id":9222968140497181079,"category":{"id":0,"name":"string"},"name":"fish","photoUrls":["string"],"tags":[{"id":0,"name":"string"}],"status":"available"},{"id":9222968140497181080,"category":{"id":0,"name":"string"},"name":"doggie","photoUrls":["string"],"tags":[{"id":0,"name":"string"}],"status":"available"},{"id":9222968140497181081,"category":{"id":0,"name":"string"},"name":"doggie","photoUrls":["string"],"tags":[{"id":0,"name":"string"}],"status":"available"},{"id":9222968140497181082,"category":{"id":0,"name":"string"},"name":"doggie","photoUrls":["string"],"tags":[{"id":0,"name":"string"}],"status":"available"},{"id":9222968140497181083,"category":{"id":0,"name":"string"},"name":"fish","photoUrls":["string"],"tags":[{"id":0,"name":"string"}],"status":"available"},{"id":9222968140497181085,"category":{"id":0,"name":"string"},"name":"doggie","photoUrls":["string"],"tags":[{"id":0,"name":"string"}],"status":"available"},{"id":9222968140497181132,"category":{"id":0,"name":"string"},"name":"fish","photoUrls":["string"],"tags":[{"id":0,"name":"string"}],"status":"available"},{"id":9222968140497181133,"category":{"id":0,"name":"string"},"name":"fish","photoUrls":["string"],"tags":[{"id":0,"name":"string"}],"status":"available"},{"id":9222968140497181134,"category":{"id":0,"name":"string"},"name":"doggie","photoUrls":["string"],"tags":[{"id":0,"name":"string"}],"status":"available"},{"id":9222968140497181135,"category":{"id":234929347298579234,"name":"string"},"name":"doggie","photoUrls":["string"],"tags":[{"id":0,"name":"string"}],"status":"available"},{"id":9222968140497181137,"category":{"id":0,"name":"string"},"name":"doggie","photoUrls":["string"],"tags":[{"id":0,"name":"string"}],"status":"available"},{"id":9222968140497181138,"category":{"id":0,"name":"string"},"name":"doggie","photoUrls":["string"],"tags":[{"id":0,"name":"string"}],"status":"available"},{"id":9222968140497181139,"category":{"id":0,"name":"string"},"name":"doggie","photoUrls":["string"],"tags":[{"id":0,"name":"string"}],"status":"available"},{"id":9222968140497181140,"category":{"id":0,"name":"string"},"name":"doggie","photoUrls":["string"],"tags":[{"id":0,"name":"string"}],"status":"available"},{"id":9222968140497181141,"category":{"id":0,"name":"string"},"name":"doggie","photoUrls":["string"],"tags":[{"id":0,"name":"string"}],"status":"available"},{"id":9222968140497181142,"category":{"id":0,"name":"string"},"name":"doggie","photoUrls":["string"],"tags":[{"id":0,"name":"string"}],"status":"available"},{"id":9222968140497181143,"category":{"id":0,"name":"string"},"name":"doggie","photoUrls":["string"],"tags":[{"id":0,"name":"string"}],"status":"available"},{"id":9222968140497181144,"category":{"id":0,"name":"string"},"name":"doggie","photoUrls":["string"],"tags":[{"id":0,"name":"string"}],"status":"available"},{"id":9222968140497181145,"category":{"id":0,"name":"string"},"name":"doggie","photoUrls":["string"],"tags":[{"id":0,"name":"string"}],"status":"available"},{"id":9222968140497181146,"category":{"id":0,"name":"string"},"name":"doggie","photoUrls":["string"],"tags":[{"id":0,"name":"string"}],"status":"available"},{"id":9222968140497181147,"category":{"id":0,"name":"string"},"name":"doggie","photoUrls":["string"],"tags":[{"id":0,"name":"string"}],"status":"available"},{"id":9222968140497181148,"category":{"id":0,"name":"string"},"name":"doggie","photoUrls":["string"],"tags":[{"id":0,"name":"string"}],"status":"available"},{"id":9222968140497181149,"category":{"id":0,"name":"string"},"name":"doggie","photoUrls":["string"],"tags":[{"id":0,"name":"string"}],"status":"available"},{"id":9222968140497181150,"category":{"id":0,"name":"string"},"name":"fish","photoUrls":["string"],"tags":[{"id":0,"name":"string"}],"status":"available"},{"id":9222968140497181151,"category":{"id":0,"name":"string"},"name":"doggie","photoUrls":["string"],"tags":[{"id":0,"name":"string"}],"status":"available"},{"id":9222968140497181152,"category":{"id":0,"name":"string"},"name":"doggie","photoUrls":["string"],"tags":[{"id":0,"name":"string"}],"status":"available"},{"id":9222968140497181153,"category":{"id":0,"name":"string"},"name":"doggie","photoUrls":["string"],"tags":[{"id":0,"name":"string"}],"status":"available"},{"id":9222968140497181154,"category":{"id":0,"name":"string"},"name":"fish","photoUrls":["string"],"tags":[{"id":0,"name":"string"}],"status":"available"},{"id":1000,"category":{"id":1000,"name":"string"},"name":"T-Rex","photoUrls":["string"],"tags":[{"id":1000,"name":"string"}],"status":"available"},{"id":9222968140491042131,"category":{"id":0,"name":"string"},"name":"doggie","photoUrls":["string"],"tags":[{"id":0,"name":"string"}],"status":"available"},{"id":9222968140497181192,"category":{"id":0,"name":"string"},"name":"fish","photoUrls":["string"],"tags":[{"id":0,"name":"string"}],"status":"available"},{"id":9222968140497181193,"category":{"id":0,"name":"string"},"name":"fish","photoUrls":["string"],"tags":[{"id":0,"name":"string"}],"status":"available"},{"id":9222968140497181195,"category":{"id":0,"name":"string"},"name":"fish","photoUrls":["string"],"tags":[{"id":0,"name":"string"}],"status":"available"},{"id":9222968140497181198,"category":{"id":0,"name":"string"},"name":"doggie","photoUrls":["string"],"tags":[{"id":0,"name":"string"}],"status":"available"},{"id":9222968140497181199,"category":{"id":0,"name":"string"},"name":"doggie","photoUrls":["string"],"tags":[{"id":0,"name":"string"}],"status":"available"},{"id":9222968140497181200,"category":{"id":0,"name":"string"},"name":"doggie","photoUrls":["string"],"tags":[{"id":0,"name":"string"}],"status":"available"},{"id":9222968140497181201,"category":{"id":0,"name":"string"},"name":"doggie","photoUrls":["string"],"tags":[{"id":0,"name":"string"}],"status":"available"},{"id":9222968140497181202,"category":{"id":0,"name":"string"},"name":"doggie","photoUrls":["string"],"tags":[{"id":0,"name":"string"}],"status":"available"},{"id":9222968140497181203,"category":{"id":0,"name":"string"},"name":"doggie","photoUrls":["string"],"tags":[{"id":0,"name":"string"}],"status":"available"},{"id":9222968140497181204,"category":{"id":0,"name":"string"},"name":"doggie","photoUrls":["string"],"tags":[{"id":0,"name":"string"}],"status":"available"},{"id":9222968140497181205,"category":{"id":0,"name":"string"},"name":"doggie","photoUrls":["string"],"tags":[{"id":0,"name":"string"}],"status":"available"},{"id":9222968140497181206,"category":{"id":0,"name":"string"},"name":"doggie","photoUrls":["string"],"tags":[{"id":0,"name":"string"}],"status":"available"},{"id":9222968140497181207,"category":{"id":0,"name":"string"},"name":"doggie","photoUrls":["string"],"tags":[{"id":0,"name":"string"}],"status":"available"},{"id":9222968140497181208,"category":{"id":0,"name":"string"},"name":"doggie","photoUrls":["string"],"tags":[{"id":0,"name":"string"}],"status":"available"},{"id":9222968140497181209,"category":{"id":0,"name":"string"},"name":"doggie","photoUrls":["string"],"tags":[{"id":0,"name":"string"}],"status":"available"},{"id":9222968140497181210,"category":{"id":0,"name":"string"},"name":"fish","photoUrls":["string"],"tags":[{"id":0,"name":"string"}],"status":"available"},{"id":9222968140497181211,"category":{"id":0,"name":"string"},"name":"doggie","photoUrls":["string"],"tags":[{"id":0,"name":"string"}],"status":"available"},{"id":9222968140497181212,"category":{"id":0,"name":"string"},"name":"doggie","photoUrls":["string"],"tags":[{"id":0,"name":"string"}],"status":"available"},{"id":9222968140497181213,"category":{"id":0,"name":"string"},"name":"doggie","photoUrls":["string"],"tags":[{"id":0,"name":"string"}],"status":"available"},{"id":9222968140497181214,"category":{"id":0,"name":"string"},"name":"fish","photoUrls":["string"],"tags":[{"id":0,"name":"string"}],"status":"available"},{"id":9222968140497181219,"category":{"id":0,"name":"string"},"name":"fish","photoUrls":["string"],"tags":[{"id":0,"name":"string"}],"status":"available"},{"id":9222968140497180179,"category":{"id":0,"name":"string"},"name":"test","photoUrls":["string"],"tags":[{"id":0,"name":"string"}],"status":"available"},{"id":112233,"category":{"id":30,"name":"Eq-dog"},"name":"Postman","photoUrls":["URLLink"],"tags":[{"id":10,"name":"Doberman"}],"status":"available"},{"id":9222968140497181220,"category":{"id":0,"name":"burhan"},"name":"doggie","photoUrls":["string"],"tags":[{"id":0,"name":"pet"}],"status":"available"},{"id":9222968140497181224,"category":{"id":0,"name":"string"},"name":"doggie","photoUrls":["string"],"tags":[{"id":0,"name":"string"}],"status":"available"},{"id":9222968140497181225,"category":{"id":0,"name":"string"},"name":"doggie","photoUrls":["string"],"tags":[{"id":0,"name":"string"}],"status":"available"},{"id":9222968140497181239,"category":{"id":0,"name":"string"},"name":"fish","photoUrls":["string"],"tags":[{"id":0,"name":"string"}],"status":"available"},{"id":9222968140497181240,"category":{"id":0,"name":"string"},"name":"fish","photoUrls":["string"],"tags":[{"id":0,"name":"string"}],"status":"available"},{"id":9222968140497181243,"category":{"id":0,"name":"string"},"name":"fetch","photoUrls":["string"],"tags":[{"id":0,"name":"string"}],"status":"available"},{"id":9222968140497181244,"category":{"id":0,"name":"string"},"name":"Puff","photoUrls":["string"],"tags":[{"id":0,"name":"string"}],"status":"available"},{"id":9222968140497181245,"category":{"id":0,"name":"string"},"name":"doggie","photoUrls":["string"],"tags":[{"id":0,"name":"string"}],"status":"available"},{"id":9222968140497181246,"category":{"id":0,"name":"string"},"name":"doggie","photoUrls":["string"],"tags":[{"id":0,"name":"string"}],"status":"available"},{"id":9222968140497181247,"category":{"id":0,"name":"string"},"name":"doggie","photoUrls":["string"],"tags":[{"id":0,"name":"string"}],"status":"available"},{"id":9222968140497181248,"category":{"id":0,"name":"string"},"name":"doggie","photoUrls":["string"],"tags":[{"id":0,"name":"string"}],"status":"available"},{"id":9222968140497181249,"category":{"id":0,"name":"string"},"name":"doggie","photoUrls":["string"],"tags":[{"id":0,"name":"string"}],"status":"available"},{"id":9222968140497181250,"category":{"id":0,"name":"string"},"name":"doggie","photoUrls":["string"],"tags":[{"id":0,"name":"string"}],"status":"available"},{"id":9222968140497181251,"category":{"id":0,"name":"string"},"name":"doggie","photoUrls":["string"],"tags":[{"id":0,"name":"string"}],"status":"available"},{"id":9222968140497181252,"category":{"id":0,"name":"string"},"name":"doggie","photoUrls":["string"],"tags":[{"id":0,"name":"string"}],"status":"available"},{"id":9222968140497181253,"category":{"id":0,"name":"string"},"name":"doggie","photoUrls":["string"],"tags":[{"id":0,"name":"string"}],"status":"available"},{"id":9222968140497181254,"category":{"id":0,"name":"string"},"name":"doggie","photoUrls":["string"],"tags":[{"id":0,"name":"string"}],"status":"available"},{"id":9222968140497181255,"category":{"id":0,"name":"string"},"name":"doggie","photoUrls":["string"],"tags":[{"id":0,"name":"string"}],"status":"available"},{"id":9222968140497181256,"category":{"id":0,"name":"string"},"name":"doggie","photoUrls":["string"],"tags":[{"id":0,"name":"string"}],"status":"available"},{"id":9222968140497181257,"category":{"id":0,"name":"string"},"name":"doggie","photoUrls":["string"],"tags":[{"id":0,"name":"string"}],"status":"available"},{"id":9222968140497181258,"category":{"id":0,"name":"string"},"name":"doggie","photoUrls":["string"],"tags":[{"id":0,"name":"string"}],"status":"available"},{"id":9222968140497181259,"category":{"id":0,"name":"string"},"name":"doggie","photoUrls":["string"],"tags":[{"id":0,"name":"string"}],"status":"available"},{"id":9222968140497181260,"category":{"id":0,"name":"string"},"name":"fish","photoUrls":["string"],"tags":[{"id":0,"name":"string"}],"status":"available"},{"id":9222968140497181261,"category":{"id":0,"name":"string"},"name":"fish","photoUrls":["string"],"tags":[{"id":0,"name":"string"}],"status":"available"},{"id":9222968140497181262,"category":{"id":0,"name":"string"},"name":"doggie","photoUrls":["string"],"tags":[{"id":0,"name":"string"}],"status":"available"},{"id":9222968140497181283,"category":{"id":0,"name":"string"},"name":"doggie","photoUrls":["string"],"tags":[{"id":0,"name":"string"}],"status":"available"},{"id":9222968140497181286,"category":{"id":0,"name":"string"},"name":"fish","photoUrls":["string"],"tags":[{"id":0,"name":"string"}],"status":"available"},{"id":9222968140497181287,"category":{"id":0,"name":"string"},"name":"fish","photoUrls":["string"],"tags":[{"id":0,"name":"string"}],"status":"available"},{"id":9222968140497181288,"category":{"id":0,"name":"string"},"name":"doggie","photoUrls":["string"],"tags":[{"id":0,"name":"string"}],"status":"available"},{"id":9222968140497181292,"category":{"id":0,"name":"string"},"name":"doggie","photoUrls":["string"],"tags":[{"id":0,"name":"string"}],"status":"available"},{"id":9222968140497181293,"category":{"id":0,"name":"string"},"name":"doggie","photoUrls":["string"],"tags":[{"id":0,"name":"string"}],"status":"available"},{"id":9222968140497181294,"category":{"id":0,"name":"string"},"name":"doggie","photoUrls":["string"],"tags":[{"id":0,"name":"string"}],"status":"available"},{"id":9222968140497181297,"category":{"id":0,"name":"string"},"name":"doggie","photoUrls":["string"],"tags":[{"id":0,"name":"string"}],"status":"available"},{"id":9222968140497181298,"category":{"id":0,"name":"string"},"name":"doggie","photoUrls":["string"],"tags":[{"id":0,"name":"string"}],"status":"available"},{"id":9222968140497181299,"category":{"id":0,"name":"string"},"name":"doggie","photoUrls":["string"],"tags":[{"id":0,"name":"string"}],"status":"available"},{"id":9222968140497181300,"category":{"id":0,"name":"string"},"name":"doggie","photoUrls":["string"],"tags":[{"id":0,"name":"string"}],"status":"available"},{"id":9222968140497181301,"category":{"id":0,"name":"string"},"name":"doggie","photoUrls":["string"],"tags":[{"id":0,"name":"string"}],"status":"available"},{"id":9222968140497181302,"category":{"id":0,"name":"string"},"name":"doggie","photoUrls":["string"],"tags":[{"id":0,"name":"string"}],"status":"available"},{"id":9222968140497181303,"category":{"id":0,"name":"string"},"name":"doggie","photoUrls":["string"],"tags":[{"id":0,"name":"string"}],"status":"available"},{"id":9222968140497181304,"category":{"id":0,"name":"string"},"name":"doggie","photoUrls":["string"],"tags":[{"id":0,"name":"string"}],"status":"available"},{"id":9222968140497181305,"category":{"id":0,"name":"string"},"name":"doggie","photoUrls":["string"],"tags":[{"id":0,"name":"string"}],"status":"available"},{"id":9222968140497181306,"category":{"id":0,"name":"string"},"name":"doggie","photoUrls":["string"],"tags":[{"id":0,"name":"string"}],"status":"available"},{"id":9222968140497181307,"category":{"id":0,"name":"string"},"name":"doggie","photoUrls":["string"],"tags":[{"id":0,"name":"string"}],"status":"available"},{"id":9222968140497181308,"category":{"id":0,"name":"string"},"name":"doggie","photoUrls":["string"],"tags":[{"id":0,"name":"string"}],"status":"available"},{"id":9222968140497181309,"category":{"id":0,"name":"string"},"name":"doggie","photoUrls":["string"],"tags":[{"id":0,"name":"string"}],"status":"available"},{"id":9222968140497181310,"category":{"id":0,"name":"string"},"name":"doggie","photoUrls":["string"],"tags":[{"id":0,"name":"string"}],"status":"available"},{"id":9222968140497181311,"category":{"id":0,"name":"string"},"name":"doggie","photoUrls":["string"],"tags":[{"id":0,"name":"string"}],"status":"available"},{"id":9222968140497181312,"category":{"id":0,"name":"string"},"name":"doggie","photoUrls":["string"],"tags":[{"id":0,"name":"string"}],"status":"available"},{"id":9222968140497181313,"category":{"id":0,"name":"string"},"name":"doggie","photoUrls":["string"],"tags":[{"id":0,"name":"string"}],"status":"available"},{"id":9222968140497181314,"category":{"id":0,"name":"string"},"name":"doggie","photoUrls":["string"],"tags":[{"id":0,"name":"string"}],"status":"available"},{"id":9222968140497181315,"category":{"id":0,"name":"string"},"name":"fish","photoUrls":["string"],"tags":[{"id":0,"name":"string"}],"status":"available"},{"id":9222968140497181316,"category":{"id":0,"name":"string"},"name":"doggie","photoUrls":["string"],"tags":[{"id":0,"name":"string"}],"status":"available"},{"id":9222968140497181317,"category":{"id":0,"name":"string"},"name":"doggie","photoUrls":["string"],"tags":[{"id":0,"name":"string"}],"status":"available"},{"id":9222968140497181318,"category":{"id":0,"name":"string"},"name":"doggie","photoUrls":["string"],"tags":[{"id":0,"name":"string"}],"status":"available"},{"id":9222968140497181319,"category":{"id":0,"name":"string"},"name":"fish","photoUrls":["string"],"tags":[{"id":0,"name":"string"}],"status":"available"},{"id":9222968140497181320,"category":{"id":0,"name":"string"},"name":"doggie","photoUrls":["string"],"tags":[{"id":0,"name":"string"}],"status":"available"},{"id":1691,"category":{"id":0,"name":"dog"},"name":"stepan","photoUrls":["string"],"tags":[{"id":0,"name":"string"}],"status":"available"},{"id":9222968140497181335,"category":{"id":0,"name":"string"},"name":"doggie","photoUrls":["string"],"tags":[{"id":0,"name":"string"}],"status":"available"},{"id":9222968140497181336,"category":{"id":0,"name":"string"},"name":"fish","photoUrls":["string"],"tags":[{"id":0,"name":"string"}],"status":"available"},{"id":9222968140497181337,"category":{"id":0,"name":"string"},"name":"fish","photoUrls":["string"],"tags":[{"id":0,"name":"string"}],"status":"available"},{"id":9222968140497181338,"category":{"id":0,"name":"string"},"name":"doggie","photoUrls":["string"],"tags":[{"id":0,"name":"string"}],"status":"available"},{"id":9222968140497181341,"category":{"id":0,"name":"string"},"name":"doggie","photoUrls":["string"],"tags":[{"id":0,"name":"string"}],"status":"available"},{"id":9222968140497181343,"category":{"id":0,"name":"string"},"name":"doggie","photoUrls":["string"],"tags":[{"id":0,"name":"string"}],"status":"available"},{"id":9222968140497181344,"category":{"id":0,"name":"string"},"name":"doggie","photoUrls":["string"],"tags":[{"id":0,"name":"string"}],"status":"available"},{"id":9222968140497181345,"category":{"id":0,"name":"string"},"name":"doggie","photoUrls":["string"],"tags":[{"id":0,"name":"string"}],"status":"available"},{"id":9222968140497181346,"category":{"id":0,"name":"string"},"name":"doggie","photoUrls":["string"],"tags":[{"id":0,"name":"string"}],"status":"available"},{"id":9222968140497181347,"category":{"id":0,"name":"string"},"name":"doggie","photoUrls":["string"],"tags":[{"id":0,"name":"string"}],"status":"available"},{"id":9222968140497181348,"category":{"id":0,"name":"string"},"name":"doggie","photoUrls":["string"],"tags":[{"id":0,"name":"string"}],"status":"available"},{"id":9222968140497181349,"category":{"id":0,"name":"string"},"name":"doggie","photoUrls":["string"],"tags":[{"id":0,"name":"string"}],"status":"available"},{"id":9222968140497181350,"category":{"id":0,"name":"string"},"name":"doggie","photoUrls":["string"],"tags":[{"id":0,"name":"string"}],"status":"available"},{"id":9222968140497181351,"category":{"id":0,"name":"string"},"name":"doggie","photoUrls":["string"],"tags":[{"id":0,"name":"string"}],"status":"available"},{"id":9222968140497181352,"category":{"id":0,"name":"string"},"name":"doggie","photoUrls":["string"],"tags":[{"id":0,"name":"string"}],"status":"available"},{"id":9222968140497181353,"category":{"id":0,"name":"string"},"name":"doggie","photoUrls":["string"],"tags":[{"id":0,"name":"string"}],"status":"available"},{"id":9222968140497181354,"category":{"id":0,"name":"string"},"name":"doggie","photoUrls":["string"],"tags":[{"id":0,"name":"string"}],"status":"available"},{"id":9222968140497181355,"category":{"id":0,"name":"string"},"name":"fish","photoUrls":["string"],"tags":[{"id":0,"name":"string"}],"status":"available"},{"id":9222968140497181356,"category":{"id":0,"name":"string"},"name":"doggie","photoUrls":["string"],"tags":[{"id":0,"name":"string"}],"status":"available"},{"id":9222968140497181357,"category":{"id":0,"name":"string"},"name":"doggie","photoUrls":["string"],"tags":[{"id":0,"name":"string"}],"status":"available"},{"id":9222968140497181358,"category":{"id":0,"name":"string"},"name":"doggie","photoUrls":["string"],"tags":[{"id":0,"name":"string"}],"status":"available"},{"id":9222968140497181359,"category":{"id":0,"name":"string"},"name":"doggie","photoUrls":["string"],"tags":[{"id":0,"name":"string"}],"status":"available"},{"id":9222968140497181360,"category":{"id":0,"name":"string"},"name":"doggie","photoUrls":["string"],"tags":[{"id":0,"name":"string"}],"status":"available"},{"id":9222968140497181361,"category":{"id":0,"name":"string"},"name":"doggie","photoUrls":["string"],"tags":[{"id":0,"name":"string"}],"status":"available"},{"id":9222968140497181362,"category":{"id":0,"name":"string"},"name":"fish","photoUrls":["string"],"tags":[{"id":0,"name":"string"}],"status":"available"},{"id":9222968140497181388,"category":{"id":0,"name":"string"},"name":"fish","photoUrls":["string"],"tags":[{"id":0,"name":"string"}],"status":"available"},{"id":9222968140497181389,"category":{"id":0,"name":"string"},"name":"fish","photoUrls":["string"],"tags":[{"id":0,"name":"string"}],"status":"available"},{"id":9222968140497181392,"category":{"id":0,"name":"string"},"name":"doggie","photoUrls":["string"],"tags":[{"id":0,"name":"string"}],"status":"available"},{"id":9222968140497181395,"category":{"id":0,"name":"string"},"name":"doggie","photoUrls":["string"],"tags":[{"id":0,"name":"string"}],"status":"available"},{"id":9222968140497181396,"category":{"id":0,"name":"string"},"name":"doggie","photoUrls":["string"],"tags":[{"id":0,"name":"string"}],"status":"available"},{"id":9222968140497181397,"category":{"id":0,"name":"string"},"name":"doggie","photoUrls":["string"],"tags":[{"id":0,"name":"string"}],"status":"available"},{"id":9222968140497181398,"category":{"id":0,"name":"string"},"name":"doggie","photoUrls":["string"],"tags":[{"id":0,"name":"string"}],"status":"available"},{"id":9222968140497181399,"category":{"id":0,"name":"string"},"name":"doggie","photoUrls":["string"],"tags":[{"id":0,"name":"string"}],"status":"available"},{"id":9222968140497181400,"category":{"id":0,"name":"string"},"name":"doggie","photoUrls":["string"],"tags":[{"id":0,"name":"string"}],"status":"available"},{"id":9222968140497181401,"category":{"id":0,"name":"string"},"name":"doggie","photoUrls":["string"],"tags":[{"id":0,"name":"string"}],"status":"available"},{"id":9222968140497181402,"category":{"id":0,"name":"string"},"name":"doggie","photoUrls":["string"],"tags":[{"id":0,"name":"string"}],"status":"available"},{"id":9222968140497181403,"category":{"id":0,"name":"string"},"name":"doggie","photoUrls":["string"],"tags":[{"id":0,"name":"string"}],"status":"available"},{"id":9222968140497181404,"category":{"id":0,"name":"string"},"name":"doggie","photoUrls":["string"],"tags":[{"id":0,"name":"string"}],"status":"available"},{"id":9222968140497181405,"category":{"id":0,"name":"string"},"name":"doggie","photoUrls":["string"],"tags":[{"id":0,"name":"string"}],"status":"available"},{"id":9222968140497181406,"category":{"id":0,"name":"string"},"name":"doggie","photoUrls":["string"],"tags":[{"id":0,"name":"string"}],"status":"available"},{"id":9222968140497181407,"category":{"id":0,"name":"string"},"name":"doggie","photoUrls":["string"],"tags":[{"id":0,"name":"string"}],"status":"available"},{"id":9222968140497181410,"category":{"id":0,"name":"string"},"name":"fish","photoUrls":["string"],"tags":[{"id":0,"name":"string"}],"status":"available"},{"id":9222968140497181411,"category":{"id":0,"name":"string"},"name":"doggie","photoUrls":["string"],"tags":[{"id":0,"name":"string"}],"status":"available"},{"id":9222968140497181412,"category":{"id":0,"name":"string"},"name":"doggie","photoUrls":["string"],"tags":[{"id":0,"name":"string"}],"status":"available"},{"id":9222968140497181413,"category":{"id":0,"name":"string"},"name":"doggie","photoUrls":["string"],"tags":[{"id":0,"name":"string"}],"status":"available"},{"id":9222968140497181414,"category":{"id":0,"name":"string"},"name":"doggie","photoUrls":["string"],"tags":[{"id":0,"name":"string"}],"status":"available"},{"id":9222968140497181415,"category":{"id":0,"name":"string"},"name":"doggie","photoUrls":["string"],"tags":[{"id":0,"name":"string"}],"status":"available"},{"id":9222968140497181416,"category":{"id":0,"name":"string"},"name":"doggie","photoUrls":["string"],"tags":[{"id":0,"name":"string"}],"status":"available"},{"id":9222968140497181417,"category":{"id":0,"name":"string"},"name":"fish","photoUrls":["string"],"tags":[{"id":0,"name":"string"}],"status":"available"},{"id":9222968140497181418,"category":{"id":0,"name":"string"},"name":"doggie","photoUrls":["string"],"tags":[{"id":0,"name":"string"}],"status":"available"},{"id":1245,"category":{"id":1245,"name":"xyz"},"name":"xyz","photoUrls":["test"],"tags":[],"status":"available"},{"id":161,"category":{"id":0,"name":"dog"},"name":"stepan","photoUrls":["string"],"tags":[{"id":0,"name":"string"}],"status":"available"},{"id":9222968140497181447,"category":{"id":0,"name":"string"},"name":"fish","photoUrls":["string"],"tags":[{"id":0,"name":"string"}],"status":"available"},{"id":9222968140497181448,"category":{"id":0,"name":"string"},"name":"fish","photoUrls":["string"],"tags":[{"id":0,"name":"string"}],"status":"available"},{"id":9222968140497181472,"category":{"id":0,"name":"string"},"name":"doggie","photoUrls":["string"],"tags":[{"id":0,"name":"string"}],"status":"available"},{"id":9222968140497181473,"category":{"id":0,"name":"string"},"name":"doggie","photoUrls":["string"],"tags":[{"id":0,"name":"string"}],"status":"available"},{"id":9222968140497181474,"category":{"id":0,"name":"string"},"name":"doggie","photoUrls":["string"],"tags":[{"id":0,"name":"string"}],"status":"available"},{"id":9222968140497181475,"category":{"id":0,"name":"string"},"name":"doggie","photoUrls":["string"],"tags":[{"id":0,"name":"string"}],"status":"available"},{"id":9222968140497181476,"category":{"id":0,"name":"string"},"name":"doggie","photoUrls":["string"],"tags":[{"id":0,"name":"string"}],"status":"available"},{"id":9222968140497181477,"category":{"id":0,"name":"string"},"name":"doggie","photoUrls":["string"],"tags":[{"id":0,"name":"string"}],"status":"available"},{"id":9222968140497181478,"category":{"id":0,"name":"string"},"name":"doggie","photoUrls":["string"],"tags":[{"id":0,"name":"string"}],"status":"available"},{"id":9222968140497181479,"category":{"id":0,"name":"string"},"name":"doggie","photoUrls":["string"],"tags":[{"id":0,"name":"string"}],"status":"available"},{"id":9222968140497181480,"category":{"id":0,"name":"string"},"name":"doggie","photoUrls":["string"],"tags":[{"id":0,"name":"string"}],"status":"available"},{"id":9222968140497181481,"category":{"id":0,"name":"string"},"name":"doggie","photoUrls":["string"],"tags":[{"id":0,"name":"string"}],"status":"available"},{"id":9222968140497181482,"category":{"id":0,"name":"string"},"name":"doggie","photoUrls":["string"],"tags":[{"id":0,"name":"string"}],"status":"available"},{"id":9222968140497181483,"category":{"id":0,"name":"string"},"name":"doggie","photoUrls":["string"],"tags":[{"id":0,"name":"string"}],"status":"available"},{"id":9222968140497181484,"category":{"id":0,"name":"string"},"name":"doggie","photoUrls":["string"],"tags":[{"id":0,"name":"string"}],"status":"available"},{"id":9222968140497181485,"category":{"id":0,"name":"string"},"name":"fish","photoUrls":["string"],"tags":[{"id":0,"name":"string"}],"status":"available"},{"id":9222968140497181486,"category":{"id":0,"name":"string"},"name":"doggie","photoUrls":["string"],"tags":[{"id":0,"name":"string"}],"status":"available"},{"id":9222968140497181487,"category":{"id":0,"name":"string"},"name":"doggie","photoUrls":["string"],"tags":[{"id":0,"name":"string"}],"status":"available"},{"id":9222968140497181488,"category":{"id":0,"name":"string"},"name":"doggie","photoUrls":["string"],"tags":[{"id":0,"name":"string"}],"status":"available"},{"id":9222968140497181489,"category":{"id":0,"name":"string"},"name":"doggie","photoUrls":["string"],"tags":[{"id":0,"name":"string"}],"status":"available"},{"id":9222968140497181490,"category":{"id":0,"name":"string"},"name":"doggie","photoUrls":["string"],"tags":[{"id":0,"name":"string"}],"status":"available"},{"id":9222968140497181491,"category":{"id":0,"name":"string"},"name":"doggie","photoUrls":["string"],"tags":[{"id":0,"name":"string"}],"status":"available"},{"id":9222968140497181492,"category":{"id":0,"name":"string"},"name":"doggie","photoUrls":["string"],"tags":[{"id":0,"name":"string"}],"status":"available"},{"id":9222968140497181493,"category":{"id":0,"name":"string"},"name":"fish","photoUrls":["string"],"tags":[{"id":0,"name":"string"}],"status":"available"},{"id":9222968140497181494,"category":{"id":0,"name":"string"},"name":"doggie","photoUrls":["string"],"tags":[{"id":0,"name":"string"}],"status":"available"},{"id":9222968140497181495,"category":{"id":0,"name":"string"},"name":"doggie","photoUrls":["string"],"tags":[{"id":0,"name":"string"}],"status":"available"},{"id":9222968140497181496,"category":{"id":0,"name":"string"},"name":"doggie","photoUrls":["string"],"tags":[{"id":0,"name":"string"}],"status":"available"},{"id":9222968140497181510,"category":{"id":0,"name":"string"},"name":"fish","photoUrls":["string"],"tags":[{"id":0,"name":"string"}],"status":"available"},{"id":9222968140497181511,"category":{"id":0,"name":"string"},"name":"fish","photoUrls":["string"],"tags":[{"id":0,"name":"string"}],"status":"available"},{"id":9222968140497181521,"category":{"id":0,"name":"string"},"name":"doggie","photoUrls":["string"],"tags":[{"id":0,"name":"string"}],"status":"available"},{"id":9222968140497181524,"category":{"id":0,"name":"string"},"name":"doggie","photoUrls":["string"],"tags":[{"id":0,"name":"string"}],"status":"available"},{"id":9222968140497181525,"category":{"id":0,"name":"string"},"name":"doggie","photoUrls":["string"],"tags":[{"id":0,"name":"string"}],"status":"available"},{"id":9222968140497181526,"category":{"id":0,"name":"string"},"name":"doggie","photoUrls":["string"],"tags":[{"id":0,"name":"string"}],"status":"available"},{"id":9222968140497181527,"category":{"id":0,"name":"string"},"name":"doggie","photoUrls":["string"],"tags":[{"id":0,"name":"string"}],"status":"available"},{"id":9222968140497181528,"category":{"id":0,"name":"string"},"name":"doggie","photoUrls":["string"],"tags":[{"id":0,"name":"string"}],"status":"available"},{"id":9222968140497181529,"category":{"id":0,"name":"string"},"name":"doggie","photoUrls":["string"],"tags":[{"id":0,"name":"string"}],"status":"available"},{"id":9222968140497181530,"category":{"id":0,"name":"string"},"name":"doggie","photoUrls":["string"],"tags":[{"id":0,"name":"string"}],"status":"available"},{"id":9222968140497181531,"category":{"id":0,"name":"string"},"name":"doggie","photoUrls":["string"],"tags":[{"id":0,"name":"string"}],"status":"available"},{"id":9222968140497181532,"category":{"id":0,"name":"string"},"name":"doggie","photoUrls":["string"],"tags":[{"id":0,"name":"string"}],"status":"available"},{"id":9222968140497181533,"category":{"id":0,"name":"string"},"name":"doggie","photoUrls":["string"],"tags":[{"id":0,"name":"string"}],"status":"available"},{"id":9222968140497181534,"category":{"id":0,"name":"string"},"name":"doggie","photoUrls":["string"],"tags":[{"id":0,"name":"string"}],"status":"available"},{"id":9222968140497181535,"category":{"id":0,"name":"string"},"name":"doggie","photoUrls":["string"],"tags":[{"id":0,"name":"string"}],"status":"available"},{"id":9222968140497181536,"category":{"id":0,"name":"string"},"name":"fish","photoUrls":["string"],"tags":[{"id":0,"name":"string"}],"status":"available"},{"id":9222968140497181539,"category":{"id":0,"name":"string"},"name":"doggie","photoUrls":["string"],"tags":[{"id":0,"name":"string"}],"status":"available"},{"id":9222968140497181540,"category":{"id":0,"name":"string"},"name":"doggie","photoUrls":["string"],"tags":[{"id":0,"name":"string"}],"status":"available"},{"id":9222968140497181541,"category":{"id":0,"name":"string"},"name":"doggie","photoUrls":["string"],"tags":[{"id":0,"name":"string"}],"status":"available"},{"id":9222968140497181542,"category":{"id":0,"name":"string"},"name":"doggie","photoUrls":["string"],"tags":[{"id":0,"name":"string"}],"status":"available"},{"id":9222968140497181543,"category":{"id":0,"name":"string"},"name":"doggie","photoUrls":["string"],"tags":[{"id":0,"name":"string"}],"status":"available"},{"id":9222968140497181544,"category":{"id":0,"name":"string"},"name":"doggie","photoUrls":["string"],"tags":[{"id":0,"name":"string"}],"status":"available"},{"id":9222968140497181545,"category":{"id":0,"name":"string"},"name":"fish","photoUrls":["string"],"tags":[{"id":0,"name":"string"}],"status":"available"},{"id":9222968140497181546,"category":{"id":0,"name":"string"},"name":"doggie","photoUrls":["string"],"tags":[{"id":0,"name":"string"}],"status":"available"},{"id":9222968140497181547,"category":{"id":0,"name":"string"},"name":"stupid doggie","photoUrls":["string"],"tags":[{"id":0,"name":"string"}],"status":"available"},{"id":899,"category":{"id":0,"name":"string"},"name":"MonkeyFox","photoUrls":["PCF"],"tags":[{"id":0,"name":"string"}],"status":"available"},{"id":9222968140497181561,"category":{"id":0,"name":"string"},"name":"stupid doggie","photoUrls":["string"],"tags":[{"id":0,"name":"string"}],"status":"available"},{"id":9222968140497181562,"category":{"id":0,"name":"string"},"name":"fish","photoUrls":["string"],"tags":[{"id":0,"name":"string"}],"status":"available"},{"id":9222968140497181563,"category":{"id":0,"name":"string"},"name":"fish","photoUrls":["string"],"tags":[{"id":0,"name":"string"}],"status":"available"},{"id":9222968140497181564,"category":{"id":0,"name":"string"},"name":"doggie","photoUrls":["string"],"tags":[{"id":0,"name":"string"}],"status":"available"},{"id":2323,"category":{"id":0,"name":"string"},"name":"dog","photoUrls":["string"],"tags":[{"id":0,"name":"tomy"}],"status":"available"},{"id":9222968140497181566,"category":{"id":0,"name":"string"},"name":"stupid doggie","photoUrls":["string"],"tags":[{"id":0,"name":"string"}],"status":"available"},{"id":11,"category":{"id":1,"name":"family"},"name":"dog family","photoUrls":["string"],"tags":[{"id":0,"name":"string"}],"status":"available"},{"id":9222968140497181580,"category":{"id":0,"name":"string"},"name":"doggie","photoUrls":["string"],"tags":[{"id":0,"name":"string"}],"status":"available"},{"id":9222968140497181581,"category":{"id":0,"name":"string"},"name":"doggie","photoUrls":["string"],"tags":[{"id":0,"name":"string"}],"status":"available"},{"id":9222968140497181582,"category":{"id":0,"name":"string"},"name":"doggie","photoUrls":["string"],"tags":[{"id":0,"name":"string"}],"status":"available"},{"id":9222968140497181583,"category":{"id":0,"name":"string"},"name":"doggie","photoUrls":["string"],"tags":[{"id":0,"name":"string"}],"status":"available"},{"id":9222968140497181584,"category":{"id":0,"name":"string"},"name":"doggie","photoUrls":["string"],"tags":[{"id":0,"name":"string"}],"status":"available"},{"id":9222968140497181585,"category":{"id":0,"name":"string"},"name":"doggie","photoUrls":["string"],"tags":[{"id":0,"name":"string"}],"status":"available"},{"id":9222968140497181586,"category":{"id":0,"name":"string"},"name":"doggie","photoUrls":["string"],"tags":[{"id":0,"name":"string"}],"status":"available"},{"id":9222968140497181587,"category":{"id":0,"name":"string"},"name":"doggie","photoUrls":["string"],"tags":[{"id":0,"name":"string"}],"status":"available"},{"id":9222968140497181588,"category":{"id":0,"name":"string"},"name":"doggie","photoUrls":["string"],"tags":[{"id":0,"name":"string"}],"status":"available"},{"id":9222968140497181589,"category":{"id":0,"name":"string"},"name":"doggie","photoUrls":["string"],"tags":[{"id":0,"name":"string"}],"status":"available"},{"id":9222968140497181590,"category":{"id":0,"name":"string"},"name":"doggie","photoUrls":["string"],"tags":[{"id":0,"name":"string"}],"status":"available"},{"id":9222968140497181591,"category":{"id":0,"name":"string"},"name":"doggie","photoUrls":["string"],"tags":[{"id":0,"name":"string"}],"status":"available"},{"id":9222968140497181592,"category":{"id":0,"name":"string"},"name":"stupid doggie","photoUrls":["string"],"tags":[{"id":0,"name":"string"}],"status":"available"},{"id":9222968140497181593,"category":{"id":0,"name":"string"},"name":"doggie","photoUrls":["string"],"tags":[{"id":0,"name":"string"}],"status":"available"},{"id":9222968140497181594,"category":{"id":0,"name":"string"},"name":"doggie","photoUrls":["string"],"tags":[{"id":0,"name":"string"}],"status":"available"},{"id":9222968140497181595,"category":{"id":0,"name":"string"},"name":"doggie","photoUrls":["string"],"tags":[{"id":0,"name":"string"}],"status":"available"},{"id":9222968140497181596,"category":{"id":0,"name":"string"},"name":"doggie","photoUrls":["string"],"tags":[{"id":0,"name":"string"}],"status":"available"},{"id":9222968140497181597,"category":{"id":0,"name":"string"},"name":"doggie","photoUrls":["string"],"tags":[{"id":0,"name":"string"}],"status":"available"},{"id":9222968140497181598,"category":{"id":0,"name":"string"},"name":"doggie","photoUrls":["string"],"tags":[{"id":0,"name":"string"}],"status":"available"},{"id":9222968140497181599,"category":{"id":0,"name":"string"},"name":"doggie","photoUrls":["string"],"tags":[{"id":0,"name":"string"}],"status":"available"},{"id":9222968140497181600,"category":{"id":0,"name":"string"},"name":"fish","photoUrls":["string"],"tags":[{"id":0,"name":"string"}],"status":"available"},{"id":9222968140497181601,"category":{"id":0,"name":"string"},"name":"fish","photoUrls":["string"],"tags":[{"id":0,"name":"string"}],"status":"available"},{"id":9222968140497181602,"category":{"id":0,"name":"string"},"name":"doggie","photoUrls":["string"],"tags":[{"id":0,"name":"string"}],"status":"available"},{"id":9222968140497181616,"category":{"id":0,"name":"string"},"name":"fish","photoUrls":["string"],"tags":[{"id":0,"name":"string"}],"status":"available"},{"id":9222968140497181617,"category":{"id":0,"name":"string"},"name":"fish","photoUrls":["string"],"tags":[{"id":0,"name":"string"}],"status":"available"},{"id":9222968140497181634,"category":{"id":0,"name":"string"},"name":"doggie","photoUrls":["string"],"tags":[{"id":0,"name":"string"}],"status":"available"},{"id":9222968140497181635,"category":{"id":0,"name":"string"},"name":"doggie","photoUrls":["string"],"tags":[{"id":0,"name":"string"}],"status":"available"},{"id":9222968140497181636,"category":{"id":0,"name":"string"},"name":"doggie","photoUrls":["string"],"tags":[{"id":0,"name":"string"}],"status":"available"},{"id":9222968140497181637,"category":{"id":0,"name":"string"},"name":"doggie","photoUrls":["string"],"tags":[{"id":0,"name":"string"}],"status":"available"},{"id":9222968140497181638,"category":{"id":0,"name":"string"},"name":"doggie","photoUrls":["string"],"tags":[{"id":0,"name":"string"}],"status":"available"},{"id":9222968140497181639,"category":{"id":0,"name":"string"},"name":"doggie","photoUrls":["string"],"tags":[{"id":0,"name":"string"}],"status":"available"},{"id":9222968140497181640,"category":{"id":0,"name":"string"},"name":"doggie","photoUrls":["string"],"tags":[{"id":0,"name":"string"}],"status":"available"},{"id":9222968140497181641,"category":{"id":0,"name":"string"},"name":"doggie","photoUrls":["string"],"tags":[{"id":0,"name":"string"}],"status":"available"},{"id":9222968140497181642,"category":{"id":0,"name":"string"},"name":"doggie","photoUrls":["string"],"tags":[{"id":0,"name":"string"}],"status":"available"},{"id":9222968140497181643,"category":{"id":0,"name":"string"},"name":"doggie","photoUrls":["string"],"tags":[{"id":0,"name":"string"}],"status":"available"},{"id":9222968140497181644,"category":{"id":0,"name":"string"},"name":"doggie","photoUrls":["string"],"tags":[{"id":0,"name":"string"}],"status":"available"},{"id":9222968140497181645,"category":{"id":0,"name":"string"},"name":"doggie","photoUrls":["string"],"tags":[{"id":0,"name":"string"}],"status":"available"},{"id":9222968140497181646,"category":{"id":0,"name":"string"},"name":"doggie","photoUrls":["string"],"tags":[{"id":0,"name":"string"}],"status":"available"},{"id":9222968140497181647,"category":{"id":0,"name":"string"},"name":"fish","photoUrls":["string"],"tags":[{"id":0,"name":"string"}],"status":"available"},{"id":9222968140497181648,"category":{"id":0,"name":"string"},"name":"doggie","photoUrls":["string"],"tags":[{"id":0,"name":"string"}],"status":"available"},{"id":9222968140497181649,"category":{"id":0,"name":"string"},"name":"doggie","photoUrls":["string"],"tags":[{"id":0,"name":"string"}],"status":"available"},{"id":9222968140497181650,"category":{"id":0,"name":"string"},"name":"doggie","photoUrls":["string"],"tags":[{"id":0,"name":"string"}],"status":"available"},{"id":9222968140497181653,"category":{"id":0,"name":"string"},"name":"doggie","photoUrls":["string"],"tags":[{"id":0,"name":"string"}],"status":"available"},{"id":9222968140497181654,"category":{"id":0,"name":"string"},"name":"doggie","photoUrls":["string"],"tags":[{"id":0,"name":"string"}],"status":"available"},{"id":9222968140497181655,"category":{"id":0,"name":"string"},"name":"doggie","photoUrls":["string"],"tags":[{"id":0,"name":"string"}],"status":"available"},{"id":9222968140497181656,"category":{"id":0,"name":"string"},"name":"fish","photoUrls":["string"],"tags":[{"id":0,"name":"string"}],"status":"available"},{"id":9222968140497181659,"category":{"id":0,"name":"string"},"name":"stupid doggie","photoUrls":["string"],"tags":[{"id":0,"name":"string"}],"status":"available"},{"id":9222968140497181673,"category":{"id":0,"name":"string"},"name":"fish","photoUrls":["string"],"tags":[{"id":0,"name":"string"}],"status":"available"},{"id":9222968140497181674,"category":{"id":0,"name":"puppy"},"name":"doggie","photoUrls":["string"],"tags":[{"id":0,"name":"Charlie"}],"status":"available"},{"id":9222968140497181675,"name":"siyaan","photoUrls":[],"tags":[],"status":"available"},{"id":9222968140497181677,"category":{"id":0,"name":"string"},"name":"fish","photoUrls":["string"],"tags":[{"id":0,"name":"string"}],"status":"available"},{"id":9222968140497181680,"category":{"id":0,"name":"string"},"name":"doggie","photoUrls":["string"],"tags":[{"id":0,"name":"string"}],"status":"available"},{"id":9222968140497181682,"category":{"id":0,"name":"string"},"name":"doggie","photoUrls":["string"],"tags":[{"id":0,"name":"string"}],"status":"available"},{"id":9222968140497181683,"category":{"id":0,"name":"string"},"name":"doggie","photoUrls":["string"],"tags":[{"id":0,"name":"string"}],"status":"available"},{"id":9222968140497181684,"category":{"id":0,"name":"string"},"name":"doggie","photoUrls":["string"],"tags":[{"id":0,"name":"string"}],"status":"available"},{"id":9222968140497181685,"category":{"id":0,"name":"string"},"name":"doggie","photoUrls":["string"],"tags":[{"id":0,"name":"string"}],"status":"available"},{"id":9222968140497181686,"category":{"id":0,"name":"string"},"name":"doggie","photoUrls":["string"],"tags":[{"id":0,"name":"string"}],"status":"available"},{"id":9222968140497181687,"category":{"id":0,"name":"string"},"name":"doggie","photoUrls":["string"],"tags":[{"id":0,"name":"string"}],"status":"available"},{"id":9222968140497181688,"category":{"id":0,"name":"string"},"name":"doggie","photoUrls":["string"],"tags":[{"id":0,"name":"string"}],"status":"available"},{"id":9222968140497181689,"category":{"id":0,"name":"string"},"name":"doggie","photoUrls":["string"],"tags":[{"id":0,"name":"string"}],"status":"available"},{"id":9222968140497181690,"category":{"id":0,"name":"string"},"name":"doggie","photoUrls":["string"],"tags":[{"id":0,"name":"string"}],"status":"available"},{"id":9222968140497181691,"category":{"id":0,"name":"string"},"name":"doggie","photoUrls":["string"],"tags":[{"id":0,"name":"string"}],"status":"available"},{"id":9222968140497181692,"category":{"id":0,"name":"string"},"name":"doggie","photoUrls":["string"],"tags":[{"id":0,"name":"string"}],"status":"available"},{"id":9222968140497181693,"category":{"id":0,"name":"string"},"name":"doggie","photoUrls":["string"],"tags":[{"id":0,"name":"string"}],"status":"available"},{"id":9222968140497181694,"category":{"id":0,"name":"string"},"name":"fish","photoUrls":["string"],"tags":[{"id":0,"name":"string"}],"status":"available"},{"id":9222968140497181695,"category":{"id":0,"name":"string"},"name":"doggie","photoUrls":["string"],"tags":[{"id":0,"name":"string"}],"status":"available"},{"id":9222968140497181696,"category":{"id":0,"name":"string"},"name":"doggie","photoUrls":["string"],"tags":[{"id":0,"name":"string"}],"status":"available"},{"id":9222968140497181697,"category":{"id":0,"name":"string"},"name":"doggie","photoUrls":["string"],"tags":[{"id":0,"name":"string"}],"status":"available"},{"id":9222968140497181698,"category":{"id":0,"name":"string"},"name":"doggie","photoUrls":["string"],"tags":[{"id":0,"name":"string"}],"status":"available"},{"id":9222968140497181699,"category":{"id":0,"name":"string"},"name":"doggie","photoUrls":["string"],"tags":[{"id":0,"name":"string"}],"status":"available"},{"id":9222968140497181700,"category":{"id":0,"name":"string"},"name":"doggie","photoUrls":["string"],"tags":[{"id":0,"name":"string"}],"status":"available"},{"id":9222968140497181701,"category":{"id":0,"name":"string"},"name":"fish","photoUrls":["string"],"tags":[{"id":0,"name":"string"}],"status":"available"},{"id":9222968140497181722,"category":{"id":0,"name":"string"},"name":"fish","photoUrls":["string"],"tags":[{"id":0,"name":"string"}],"status":"available"},{"id":9222968140497181723,"category":{"id":0,"name":"string"},"name":"fish","photoUrls":["string"],"tags":[{"id":0,"name":"string"}],"status":"available"},{"id":9222968140497181734,"category":{"id":0,"name":"string"},"name":"doggie","photoUrls":["string"],"tags":[{"id":0,"name":"string"}],"status":"available"},{"id":9222968140497181735,"category":{"id":0,"name":"string"},"name":"doggie","photoUrls":["string"],"tags":[{"id":0,"name":"string"}],"status":"available"},{"id":9222968140497181736,"category":{"id":0,"name":"string"},"name":"doggie","photoUrls":["string"],"tags":[{"id":0,"name":"string"}],"status":"available"},{"id":9222968140497181737,"category":{"id":0,"name":"string"},"name":"doggie","photoUrls":["string"],"tags":[{"id":0,"name":"string"}],"status":"available"},{"id":9222968140497181738,"category":{"id":0,"name":"string"},"name":"doggie","photoUrls":["string"],"tags":[{"id":0,"name":"string"}],"status":"available"},{"id":9222968140497181739,"category":{"id":0,"name":"string"},"name":"doggie","photoUrls":["string"],"tags":[{"id":0,"name":"string"}],"status":"available"},{"id":9222968140497181740,"category":{"id":0,"name":"string"},"name":"doggie","photoUrls":["string"],"tags":[{"id":0,"name":"string"}],"status":"available"},{"id":9222968140497181741,"category":{"id":0,"name":"string"},"name":"doggie","photoUrls":["string"],"tags":[{"id":0,"name":"string"}],"status":"available"},{"id":9222968140497181742,"category":{"id":0,"name":"string"},"name":"doggie","photoUrls":["string"],"tags":[{"id":0,"name":"string"}],"status":"available"},{"id":9222968140497181743,"category":{"id":0,"name":"string"},"name":"doggie","photoUrls":["string"],"tags":[{"id":0,"name":"string"}],"status":"available"},{"id":9222968140497181744,"category":{"id":0,"name":"string"},"name":"doggie","photoUrls":["string"],"tags":[{"id":0,"name":"string"}],"status":"available"},{"id":9222968140497181745,"category":{"id":0,"name":"string"},"name":"doggie","photoUrls":["string"],"tags":[{"id":0,"name":"string"}],"status":"available"},{"id":9222968140497181746,"category":{"id":0,"name":"string"},"name":"doggie","photoUrls":["string"],"tags":[{"id":0,"name":"string"}],"status":"available"},{"id":9222968140497181747,"category":{"id":0,"name":"string"},"name":"doggie","photoUrls":["string"],"tags":[{"id":0,"name":"string"}],"status":"available"},{"id":9222968140497181748,"category":{"id":0,"name":"string"},"name":"doggie","photoUrls":["string"],"tags":[{"id":0,"name":"string"}],"status":"available"},{"id":9222968140497181749,"category":{"id":0,"name":"string"},"name":"doggie","photoUrls":["string"],"tags":[{"id":0,"name":"string"}],"status":"available"},{"id":9222968140497181750,"category":{"id":0,"name":"string"},"name":"doggie","photoUrls":["string"],"tags":[{"id":0,"name":"string"}],"status":"available"},{"id":9222968140497181751,"category":{"id":0,"name":"string"},"name":"doggie","photoUrls":["string"],"tags":[{"id":0,"name":"string"}],"status":"available"},{"id":9222968140497181752,"category":{"id":0,"name":"string"},"name":"fish","photoUrls":["string"],"tags":[{"id":0,"name":"string"}],"status":"available"},{"id":9222968140497181755,"category":{"id":0,"name":"string"},"name":"fish","photoUrls":["string"],"tags":[{"id":0,"name":"string"}],"status":"available"},{"id":9222968140497181771,"category":{"id":0,"name":"string"},"name":"fish","photoUrls":["string"],"tags":[{"id":0,"name":"string"}],"status":"available"},{"id":9222968140497181772,"category":{"id":0,"name":"string"},"name":"fish","photoUrls":["string"],"tags":[{"id":0,"name":"string"}],"status":"available"},{"id":9222968140497181815,"category":{"id":0,"name":"string"},"name":"doggie","photoUrls":["string"],"tags":[{"id":0,"name":"string"}],"status":"available"},{"id":9222968140497181816,"category":{"id":0,"name":"string"},"name":"doggie","photoUrls":["string"],"tags":[{"id":0,"name":"string"}],"status":"available"},{"id":9222968140497181817,"category":{"id":0,"name":"string"},"name":"doggie","photoUrls":["string"],"tags":[{"id":0,"name":"string"}],"status":"available"},{"id":9222968140497181818,"category":{"id":0,"name":"string"},"name":"doggie","photoUrls":["string"],"tags":[{"id":0,"name":"string"}],"status":"available"},{"id":9222968140497181819,"category":{"id":0,"name":"string"},"name":"doggie","photoUrls":["string"],"tags":[{"id":0,"name":"string"}],"status":"available"},{"id":9222968140497181820,"category":{"id":0,"name":"string"},"name":"doggie","photoUrls":["string"],"tags":[{"id":0,"name":"string"}],"status":"available"},{"id":111,"category":{"id":-44383024,"name":"in proident"},"name":"lucky","photoUrls":["lucky.com","yes"],"tags":[{"id":34886055,"name":"ullamco sint eiusmod nisi mollit"},{"id":-46536470,"name":"eu magna ut irure"}],"status":"available"},{"id":9222968140497181822,"category":{"id":0,"name":"string"},"name":"doggie","photoUrls":["string"],"tags":[{"id":0,"name":"string"}],"status":"available"},{"id":9222968140497181823,"category":{"id":0,"name":"string"},"name":"doggie","photoUrls":["string"],"tags":[{"id":0,"name":"string"}],"status":"available"},{"id":9222968140497181824,"category":{"id":0,"name":"string"},"name":"doggie","photoUrls":["string"],"tags":[{"id":0,"name":"string"}],"status":"available"},{"id":9222968140497181825,"category":{"id":0,"name":"string"},"name":"doggie","photoUrls":["string"],"tags":[{"id":0,"name":"string"}],"status":"available"},{"id":9222968140497181826,"category":{"id":0,"name":"string"},"name":"doggie","photoUrls":["string"],"tags":[{"id":0,"name":"string"}],"status":"available"},{"id":9222968140497181827,"category":{"id":0,"name":"string"},"name":"doggie","photoUrls":["string"],"tags":[{"id":0,"name":"string"}],"status":"available"},{"id":9222968140497181828,"category":{"id":0,"name":"string"},"name":"doggie","photoUrls":["string"],"tags":[{"id":0,"name":"string"}],"status":"available"},{"id":9222968140497181829,"category":{"id":0,"name":"string"},"name":"doggie","photoUrls":["string"],"tags":[{"id":0,"name":"string"}],"status":"available"},{"id":9222968140497181830,"category":{"id":0,"name":"string"},"name":"doggie","photoUrls":["string"],"tags":[{"id":0,"name":"string"}],"status":"available"},{"id":9222968140497181831,"category":{"id":0,"name":"string"},"name":"doggie","photoUrls":["string"],"tags":[{"id":0,"name":"string"}],"status":"available"},{"id":9222968140497181832,"category":{"id":0,"name":"string"},"name":"doggie","photoUrls":["string"],"tags":[{"id":0,"name":"string"}],"status":"available"},{"id":9222968140497181833,"category":{"id":0,"name":"string"},"name":"doggie","photoUrls":["string"],"tags":[{"id":0,"name":"string"}],"status":"available"},{"id":9222968140497181834,"category":{"id":0,"name":"string"},"name":"fish","photoUrls":["string"],"tags":[{"id":0,"name":"string"}],"status":"available"},{"id":9222968140497181835,"category":{"id":0,"name":"string"},"name":"fish","photoUrls":["string"],"tags":[{"id":0,"name":"string"}],"status":"available"},{"id":222,"category":{"id":-44383024,"name":"in proident"},"name":"lucky2","photoUrls":["lucky.com","yes"],"tags":[{"id":34886055,"name":"ullamco sint eiusmod nisi mollit"},{"id":-46536470,"name":"eu magna ut irure"}],"status":"available"}]